smartscalc/__init__.py
smartscalc/calculator.py
smartscalc-1.0.1.dist-info/licenses/LICENSE.md
smartscalc-1.0.1.dist-info/METADATA
smartscalc-1.0.1.dist-info/WHEEL
smartscalc-1.0.1.dist-info/top_level.txt
smartscalc-1.0.1.dist-info/RECORD
